---
title: Java-synchronziedåº•å±‚åŸç†
toc: true
date: 2021-07-28 17:57:19
tags: å¤šçº¿ç¨‹
categories: [Develop Lan,Java,å¤šçº¿ç¨‹ä¸å¹¶å‘]
---

# synchronziedåº•å±‚åŸç†

## synchronziedå››ä¸ªå±‚çº§å®ç°
- Javaä»£ç  é€šè¿‡æ·»åŠ synchronziedç»™å¯¹è±¡æˆ–è€…æ–¹æ³•æˆ–è€…ä»£ç å—
- å­—èŠ‚ç å±‚çº§é€šè¿‡ä¸€ç»„ MONITORENTER/MONITOREXITæŒ‡ä»¤
- JVMå±‚çº§ï¼šé”å‡çº§è¿‡ç¨‹
- æ±‡ç¼–æ‰§è¡Œé€šè¿‡ lock comxchgæŒ‡ä»¤ä¿è¯åŸå­æ“ä½œ


JDKæ—©æœŸï¼Œsynchronized å«åšé‡é‡çº§é”ï¼Œ å› ä¸ºç”³è¯·é”èµ„æºå¿…é¡»é€šè¿‡kernel, ç³»ç»Ÿè°ƒç”¨
```java
;hello.asm
;write(int fd, const void *buffer, size_t nbytes)

section data
    msg db "Hello", 0xA
    len equ $ - msg

section .text
global _start
_start:

    mov edx, len
    mov ecx, msg
    mov ebx, 1 ;æ–‡ä»¶æè¿°ç¬¦1 std_out
    mov eax, 4 ;writeå‡½æ•°ç³»ç»Ÿè°ƒç”¨å· 4
    int 0x80

    mov ebx, 0
    mov eax, 1 ;exitå‡½æ•°ç³»ç»Ÿè°ƒç”¨å·
    int 0x80
```

ä¼˜åŒ–åçš„synchronizedå¦‚ä¸‹ğŸ‘‡ï¼š
## Javaå±‚çº§
```java
  public static void main(String[] args) {
        Object object = new Object();
        System.out.println(ClassLayout.parseInstance(object).toPrintable());

        synchronized (object){
            System.out.println(ClassLayout.parseInstance(object).toPrintable());
        }
    }
```

## å­—èŠ‚ç å±‚çº§
```java
// access flags 0x9
  public static main([Ljava/lang/String;)V
    // parameter  args
    TRYCATCHBLOCK L0 L1 L2 null
    TRYCATCHBLOCK L2 L3 L2 null
   L4
    LINENUMBER 13 L4
    NEW java/lang/Object
    DUP
    INVOKESPECIAL java/lang/Object.<init> ()V
    ASTORE 1
   L5
    LINENUMBER 14 L5
    GETSTATIC java/lang/System.out : Ljava/io/PrintStream;
    ALOAD 1
    INVOKESTATIC org/openjdk/jol/info/ClassLayout.parseInstance (Ljava/lang/Object;)Lorg/openjdk/jol/info/ClassLayout;
    INVOKEVIRTUAL org/openjdk/jol/info/ClassLayout.toPrintable ()Ljava/lang/String;
    INVOKEVIRTUAL java/io/PrintStream.println (Ljava/lang/String;)V
   L6
    LINENUMBER 16 L6
    ALOAD 1
    DUP
    ASTORE 2
    MONITORENTER
   L0
    LINENUMBER 17 L0
    GETSTATIC java/lang/System.out : Ljava/io/PrintStream;
    ALOAD 1
    INVOKESTATIC org/openjdk/jol/info/ClassLayout.parseInstance (Ljava/lang/Object;)Lorg/openjdk/jol/info/ClassLayout;
    INVOKEVIRTUAL org/openjdk/jol/info/ClassLayout.toPrintable ()Ljava/lang/String;
    INVOKEVIRTUAL java/io/PrintStream.println (Ljava/lang/String;)V
   L7
    LINENUMBER 18 L7
    ALOAD 2
    MONITOREXIT
   L1
    GOTO L8
   L2
   FRAME FULL [[Ljava/lang/String; java/lang/Object java/lang/Object] [java/lang/Throwable]
    ASTORE 3
    ALOAD 2
    MONITOREXIT
   L3
    ALOAD 3
    ATHROW
   L8
    LINENUMBER 19 L8
   FRAME CHOP 1
    RETURN
   L9
    LOCALVARIABLE args [Ljava/lang/String; L4 L9 0
    LOCALVARIABLE object Ljava/lang/Object; L5 L9 1
    MAXSTACK = 2
    MAXLOCALS = 4
}
```
> ä¸»è¦é€šè¿‡MONITORENTER å’Œ MONITOREXIT ä¸¤ä¸ªå­—èŠ‚ç æŒ‡ä»¤æ§åˆ¶åŠ é”è¿‡ç¨‹


## JVMå±‚çº§

é€šè¿‡é”å‡çº§è¿‡ç¨‹å®ç°åŠ é”ï¼›
æ— é” -> åå‘é” -> è‡ªæ—‹é”ï¼ˆè½»é‡çº§é” è‡ªé€‚åº”é”ï¼‰-> é‡é‡çº§é”
é”å‡çº§è¿‡ç¨‹å¯ä»¥æŸ¥çœ‹ [é”å‡çº§è¿‡ç¨‹](doc:rjG4EIhi)  å¤åˆ¶ç†è§£


## æ±‡ç¼–æŒ‡ä»¤çº§åˆ«
linuxæ“ä½œç³»ç»Ÿå®‰è£…hsdisæ’ä»¶ï¼ŒæŸ¥çœ‹javaä»£ç çš„æ±‡ç¼–æŒ‡ä»¤ï¼š
```
public class T {
    static volatile int i = 0;
    
    public static void n() { i++; }
    
    public static synchronized void m() {}
    
    publics static void main(String[] args) {
        for(int j=0; j<1000_000; j++) {
            m();
            n();
        }
    }
}
```
æ‰§è¡Œä»¥ä¸‹å‘½ä»¤ï¼š
```
java -XX:+UnlockDiagnosticVMOptions -XX:+PrintAssembly T
```
- C1 Compile Level 1 (ä¸€çº§ä¼˜åŒ–)
- C2 Compile Level 2 (äºŒçº§ä¼˜åŒ–)

> æ‰¾åˆ°m() n()æ–¹æ³•çš„æ±‡ç¼–ç ï¼Œä¼šçœ‹åˆ° lock comxchg .....æŒ‡ä»¤

